simplefbchat/__init__.py
simplefbchat/simplefbchat.py
simplefbchat/detail/__init__.py
simplefbchat/detail/chat.py
simplefbchat/detail/fbbot.py
simplefbchat-0.0.4.dist-info/LICENSE
simplefbchat-0.0.4.dist-info/METADATA
simplefbchat-0.0.4.dist-info/WHEEL
simplefbchat-0.0.4.dist-info/top_level.txt
simplefbchat-0.0.4.dist-info/RECORD
