Metadata-Version: 2.1
Name: simplefbchat
Version: 0.0.4
Summary: Simple Facebook Chat library for students.
Home-page: https://github.com/chyla/simplefbchat
Author: Adam Chyła
Author-email: adam@chyla.org
License: UNKNOWN
Platform: UNKNOWN
Classifier: Programming Language :: Python :: 3
Classifier: License :: OSI Approved :: BSD License
Classifier: Operating System :: OS Independent
Requires-Dist: fbchat
